liva/__init__.py
liva/__main__.py
liva-0.1.0.dist-info/LICENSE
liva-0.1.0.dist-info/METADATA
liva-0.1.0.dist-info/WHEEL
liva-0.1.0.dist-info/entry_points.txt
liva-0.1.0.dist-info/RECORD
